Workbook

Sheet sheet1
A1: TableName | B1: In Sheet
A2: BusinessDocumentTaxTransactionStaging
A3: CurrencyStaging
A4: CustCustomerGroupEntityStaging
A5: CustCustomerV3Staging
A6: CustElectronicAddressStaging
A7: CustInvoiceJournalHeaderStaging
A8: CustInvoiceJournalLineStaging
A9: CustInvoicePackingSlipQuantityMatchStaging
A10: CustInvoiceTransStaging
A11: CustomerAgingDataStorageStaging
A12: CustomerPaymentJournalLineStaging
A13: CustPackingSlipTransStaging
... A100: WMSWarehouseLocationStaging

Sheet Sheet2
A1: Staging Table | B1: Entity Name | C1: Staguing Table | D1: In DB
A2: CustomerAttachmentsV2EntityStaging | B2: =_xlfn.XLOOKUP(A2,[1]Sheet1!$A:$A,[1]Sheet1!$B:$B,"Not found",0) -> Not found | C2: =_xlfn.XLOOKUP(A2,[1]Sheet1!$B:$B,[1]Sheet1!$A:$A,"Not found",0) -> Not found
A3: VendVendorV2Staging | B3: =_xlfn.XLOOKUP(A3,[1]Sheet1!$A:$A,[1]Sheet1!$B:$B,"Not found",0) -> Vendors V2 | C3: =_xlfn.XLOOKUP(A3,[1]Sheet1!$B:$B,[1]Sheet1!$A:$A,"Not found",0) -> Not found | D3: =_xlfn.XLOOKUP(A3,sheet1!A:A,sheet1!A:A,"Not found",0) -> VendVendorV2Staging
A4: DirPartyV2Staging | B4: =_xlfn.XLOOKUP(A4,[1]Sheet1!$A:$A,[1]Sheet1!$B:$B,"Not found",0) -> Global address book V2 | C4: =_xlfn.XLOOKUP(A4,[1]Sheet1!$B:$B,[1]Sheet1!$A:$A,"Not found",0) -> Not found | D4: =_xlfn.XLOOKUP(A4,sheet1!A:A,sheet1!A:A,"Not found",0) -> DirPartyV2Staging
A5: DirPartyContactV3Staging | B5: =_xlfn.XLOOKUP(A5,[1]Sheet1!$A:$A,[1]Sheet1!$B:$B,"Not found",0) -> Party contacts V3 | C5: =_xlfn.XLOOKUP(A5,[1]Sheet1!$B:$B,[1]Sheet1!$A:$A,"Not found",0) -> Not found | D5: =_xlfn.XLOOKUP(A5,sheet1!A:A,sheet1!A:A,"Not found",0) -> DirPartyContactV3Staging
A6: VendorDocumentAttachmentStaging | B6: =_xlfn.XLOOKUP(A6,[1]Sheet1!$A:$A,[1]Sheet1!$B:$B,"Not found",0) -> Not found | C6: =_xlfn.XLOOKUP(A6,[1]Sheet1!$B:$B,[1]Sheet1!$A:$A,"Not found",0) -> Not found | D6: =_xlfn.XLOOKUP(A6,sheet1!A:A,sheet1!A:A,"Not found",0) -> Not found
A7: EcoResEveryProductStaging | B7: =_xlfn.XLOOKUP(A7,[1]Sheet1!$A:$A,[1]Sheet1!$B:$B,"Not found",0) -> All products | C7: =_xlfn.XLOOKUP(A7,[1]Sheet1!$B:$B,[1]Sheet1!$A:$A,"Not found",0) -> Not found | D7: =_xlfn.XLOOKUP(A7,sheet1!A:A,sheet1!A:A,"Not found",0) -> EcoResEveryProductStaging
A8: EcoResProductGlobalTradeItemNumberAssignmentV2Staging | B8: =_xlfn.XLOOKUP(A8,[1]Sheet1!$A:$A,[1]Sheet1!$B:$B,"Not found",0) -> Product global trade item number assignments V2 | C8: =_xlfn.XLOOKUP(A8,[1]Sheet1!$B:$B,[1]Sheet1!$A:$A,"Not found",0) -> Not found | D8: =_xlfn.XLOOKUP(A8,sheet1!A:A,sheet1!A:A,"Not found",0) -> EcoResProductGlobalTradeItemNumberAssignmentV2Staging
A9: EcoResProductTranslationStaging | B9: =_xlfn.XLOOKUP(A9,[1]Sheet1!$A:$A,[1]Sheet1!$B:$B,"Not found",0) -> Product translations | C9: =_xlfn.XLOOKUP(A9,[1]Sheet1!$B:$B,[1]Sheet1!$A:$A,"Not found",0) -> Not found | D9: =_xlfn.XLOOKUP(A9,sheet1!A:A,sheet1!A:A,"Not found",0) -> EcoResProductTranslationStaging
A10: EcoResProductV2Staging | B10: =_xlfn.XLOOKUP(A10,[1]Sheet1!$A:$A,[1]Sheet1!$B:$B,"Not found",0) -> Products V2 | C10: =_xlfn.XLOOKUP(A10,[1]Sheet1!$B:$B,[1]Sheet1!$A:$A,"Not found",0) -> Not found | D10: =_xlfn.XLOOKUP(A10,sheet1!A:A,sheet1!A:A,"Not found",0) -> EcoResProductV2Staging
A11: EcoResProductVariantV2Staging | B11: =_xlfn.XLOOKUP(A11,[1]Sheet1!$A:$A,[1]Sheet1!$B:$B,"Not found",0) -> Product variants V2 | C11: =_xlfn.XLOOKUP(A11,[1]Sheet1!$B:$B,[1]Sheet1!$A:$A,"Not found",0) -> Not found | D11: =_xlfn.XLOOKUP(A11,sheet1!A:A,sheet1!A:A,"Not found",0) -> EcoResProductVariantV2Staging
A12: EcoResReleasedProductV2Staging | B12: =_xlfn.XLOOKUP(A12,[1]Sheet1!$A:$A,[1]Sheet1!$B:$B,"Not found",0) -> Released products V2 | C12: =_xlfn.XLOOKUP(A12,[1]Sheet1!$B:$B,[1]Sheet1!$A:$A,"Not found",0) -> Not found | D12: =_xlfn.XLOOKUP(A12,sheet1!A:A,sheet1!A:A,"Not found",0) -> EcoResReleasedProductV2Staging
A13: EcoResReleasedProductVariantV2Staging | B13: =_xlfn.XLOOKUP(A13,[1]Sheet1!$A:$A,[1]Sheet1!$B:$B,"Not found",0) -> Released product variants V2 | C13: =_xlfn.XLOOKUP(A13,[1]Sheet1!$B:$B,[1]Sheet1!$A:$A,"Not found",0) -> Not found | D13: =_xlfn.XLOOKUP(A13,sheet1!A:A,sheet1!A:A,"Not found",0) -> EcoResReleasedProductVariantV2Staging
A14: NmbCANHarmonizeStaging | B14: =_xlfn.XLOOKUP(A14,[1]Sheet1!$A:$A,[1]Sheet1!$B:$B,"Not found",0) -> CAN Harmonize Code | C14: =_xlfn.XLOOKUP(A14,[1]Sheet1!$B:$B,[1]Sheet1!$A:$A,"Not found",0) -> Not found | D14: =_xlfn.XLOOKUP(A14,sheet1!A:A,sheet1!A:A,"Not found",0) -> NmbCANHarmonizeStaging
... A86: GNLN Cust Trans Entity | B86: =_xlfn.XLOOKUP(A86,[1]Sheet1!$A:$A,[1]Sheet1!$B:$B,"Not found",0) -> Not found | C86: =_xlfn.XLOOKUP(A86,[1]Sheet1!$B:$B,[1]Sheet1!$A:$A,"Not found",0) -> GNLNCustTransStaging | D86: =_xlfn.XLOOKUP(A86,sheet1!A:A,sheet1!A:A,"Not found",0) -> Not found

Sheet Sheet3
A1: CustomerAttachmentsV2EntityStaging | B1: =_xlfn.XLOOKUP(A1,sheet1!A:A,sheet1!A:A,"NA",0) -> NA
A2: VendVendorV2Staging | B2: =_xlfn.XLOOKUP(A2,sheet1!A:A,sheet1!A:A,"NA",0) -> VendVendorV2Staging
A3: DirPartyV2Staging | B3: =_xlfn.XLOOKUP(A3,sheet1!A:A,sheet1!A:A,"NA",0) -> DirPartyV2Staging
A4: DirPartyContactV3Staging | B4: =_xlfn.XLOOKUP(A4,sheet1!A:A,sheet1!A:A,"NA",0) -> DirPartyContactV3Staging
A5: VendorDocumentAttachmentStaging | B5: =_xlfn.XLOOKUP(A5,sheet1!A:A,sheet1!A:A,"NA",0) -> NA
A6: EcoResEveryProductStaging | B6: =_xlfn.XLOOKUP(A6,sheet1!A:A,sheet1!A:A,"NA",0) -> EcoResEveryProductStaging
A7: EcoResProductGlobalTradeItemNumberAssignmentV2Staging | B7: =_xlfn.XLOOKUP(A7,sheet1!A:A,sheet1!A:A,"NA",0) -> EcoResProductGlobalTradeItemNumberAssignmentV2Staging
A8: EcoResProductTranslationStaging | B8: =_xlfn.XLOOKUP(A8,sheet1!A:A,sheet1!A:A,"NA",0) -> EcoResProductTranslationStaging
A9: EcoResProductV2Staging | B9: =_xlfn.XLOOKUP(A9,sheet1!A:A,sheet1!A:A,"NA",0) -> EcoResProductV2Staging
A10: EcoResProductVariantV2Staging | B10: =_xlfn.XLOOKUP(A10,sheet1!A:A,sheet1!A:A,"NA",0) -> EcoResProductVariantV2Staging
A11: EcoResReleasedProductV2Staging | B11: =_xlfn.XLOOKUP(A11,sheet1!A:A,sheet1!A:A,"NA",0) -> EcoResReleasedProductV2Staging
A12: EcoResReleasedProductVariantV2Staging | B12: =_xlfn.XLOOKUP(A12,sheet1!A:A,sheet1!A:A,"NA",0) -> EcoResReleasedProductVariantV2Staging
... A85: GNLNCustTransStaging | B85: =_xlfn.XLOOKUP(A85,sheet1!A:A,sheet1!A:A,"NA",0) -> GNLNCustTransStaging
